Adafruit_GPIO/FT232H.py
Adafruit_GPIO/GPIO.py
Adafruit_GPIO/I2C.py
Adafruit_GPIO/MCP230xx.py
Adafruit_GPIO/PCF8574.py
Adafruit_GPIO/PWM.py
Adafruit_GPIO/Platform.py
Adafruit_GPIO/Platformedit.py
Adafruit_GPIO/SPI.py
Adafruit_GPIO/__init__.py
MAX6675/MAX6675.py
MAX6675/__init__.py
auto_pump/__init__.py
auto_pump/your_code.py
pump_auto-1.0.0.dist-info/METADATA
pump_auto-1.0.0.dist-info/WHEEL
pump_auto-1.0.0.dist-info/top_level.txt
pump_auto-1.0.0.dist-info/RECORD
