Metadata-Version: 2.1
Name: pump-auto
Version: 1.0.0
Summary: A brief description of auto_pump package
Home-page: https://github.com/your_username/auto_pump
Author: Your Name
Author-email: your_email@example.com
Classifier: Programming Language :: Python :: 3
Classifier: License :: OSI Approved :: MIT License
Classifier: Operating System :: OS Independent
Requires-Python: >=3.6
